[{"discovered_switches": 1600, "multinet_hosts_per_switch": 0, "multinet_group_size": 1, "discovered_switches_error_code": 0, "multinet_topology_type": "linear", "used_memory_bytes": 98932688, "controller_num_threads": 430, "multinet_workers": 16, "fifteen_minute_load": 3.16, "controller_cpu_system_time": 5739.0, "controller_cwd": "/home/jenkins/nstat/controllers/odl_beryllium_rc2_pb/distribution-karaf-0.4.0-Beryllium-RC2", "controller_java_xopts": ["-Xmx8G", "-Xms8G", "-XX:+UseG1GC", "-XX:MaxPermSize=8G"], "free_memory_bytes": 164992444, "controller_vm_size": 29408509952, "controller_cpu_shares": "75", "successful_bootup_time": 520.3598201274872, "five_minute_load": 4.02, "global_sample_id": 0, "controller_statistics_period_ms": 5000, "controller_num_fds": 3385, "controller_node_ip": "192.168.100.1", "multinet_worker_topo_size": 100, "controller_cpu_user_time": 104397.0, "date": "Fri Mar  4 17:42:54 EET 2016", "max_discovered_switches": 1600, "one_minute_load": 5.06, "multinet_group_delay_ms": 5000, "multinet_size": 1600, "timestamp": 1457106174, "total_memory_bytes": 263927548, "bootup_time_secs": 520.3598201274872, "controller_port": "6653"}, {"discovered_switches": 1600, "multinet_hosts_per_switch": 0, "multinet_group_size": 5, "discovered_switches_error_code": 0, "multinet_topology_type": "linear", "used_memory_bytes": 98219336, "controller_num_threads": 430, "multinet_workers": 16, "fifteen_minute_load": 3.28, "controller_cpu_system_time": 2635.0, "controller_cwd": "/home/jenkins/nstat/controllers/odl_beryllium_rc2_pb/distribution-karaf-0.4.0-Beryllium-RC2", "controller_java_xopts": ["-Xmx8G", "-Xms8G", "-XX:+UseG1GC", "-XX:MaxPermSize=8G"], "free_memory_bytes": 165707804, "controller_vm_size": 29419319296, "controller_cpu_shares": "75", "successful_bootup_time": 122.41307187080383, "five_minute_load": 3.8, "global_sample_id": 1, "controller_statistics_period_ms": 5000, "controller_num_fds": 3385, "controller_node_ip": "192.168.100.1", "multinet_worker_topo_size": 100, "controller_cpu_user_time": 53135.0, "date": "Fri Mar  4 17:48:48 EET 2016", "max_discovered_switches": 1600, "one_minute_load": 4.26, "multinet_group_delay_ms": 5000, "multinet_size": 1600, "timestamp": 1457106528, "total_memory_bytes": 263927548, "bootup_time_secs": 122.41307187080383, "controller_port": "6653"}, {"discovered_switches": 3200, "multinet_hosts_per_switch": 0, "multinet_group_size": 1, "discovered_switches_error_code": 0, "multinet_topology_type": "linear", "used_memory_bytes": 102476840, "controller_num_threads": 543, "multinet_workers": 16, "fifteen_minute_load": 4.97, "controller_cpu_system_time": 13606.0, "controller_cwd": "/home/jenkins/nstat/controllers/odl_beryllium_rc2_pb/distribution-karaf-0.4.0-Beryllium-RC2", "controller_java_xopts": ["-Xmx8G", "-Xms8G", "-XX:+UseG1GC", "-XX:MaxPermSize=8G"], "free_memory_bytes": 161450980, "controller_vm_size": 29538983936, "controller_cpu_shares": "75", "successful_bootup_time": 1036.259665966034, "five_minute_load": 7.5, "global_sample_id": 2, "controller_statistics_period_ms": 5000, "controller_num_fds": 4985, "controller_node_ip": "192.168.100.1", "multinet_worker_topo_size": 200, "controller_cpu_user_time": 224233.0, "date": "Fri Mar  4 18:10:01 EET 2016", "max_discovered_switches": 3200, "one_minute_load": 11.76, "multinet_group_delay_ms": 5000, "multinet_size": 3200, "timestamp": 1457107800, "total_memory_bytes": 263927548, "bootup_time_secs": 1036.259665966034, "controller_port": "6653"}, {"discovered_switches": 3200, "multinet_hosts_per_switch": 0, "multinet_group_size": 5, "discovered_switches_error_code": 0, "multinet_topology_type": "linear", "used_memory_bytes": 101794268, "controller_num_threads": 531, "multinet_workers": 16, "fifteen_minute_load": 11.26, "controller_cpu_system_time": 6980.0, "controller_cwd": "/home/jenkins/nstat/controllers/odl_beryllium_rc2_pb/distribution-karaf-0.4.0-Beryllium-RC2", "controller_java_xopts": ["-Xmx8G", "-Xms8G", "-XX:+UseG1GC", "-XX:MaxPermSize=8G"], "free_memory_bytes": 162133036, "controller_vm_size": 29526286336, "controller_cpu_shares": "75", "successful_bootup_time": 347.015412569046, "five_minute_load": 19.22, "global_sample_id": 3, "controller_statistics_period_ms": 5000, "controller_num_fds": 4985, "controller_node_ip": "192.168.100.1", "multinet_worker_topo_size": 200, "controller_cpu_user_time": 130535.0, "date": "Fri Mar  4 18:19:40 EET 2016", "max_discovered_switches": 3200, "one_minute_load": 24.61, "multinet_group_delay_ms": 5000, "multinet_size": 3200, "timestamp": 1457108380, "total_memory_bytes": 263927548, "bootup_time_secs": 347.015412569046, "controller_port": "6653"}, {"discovered_switches": 4800, "multinet_hosts_per_switch": 0, "multinet_group_size": 1, "discovered_switches_error_code": 0, "multinet_topology_type": "linear", "used_memory_bytes": 106561272, "controller_num_threads": 637, "multinet_workers": 16, "fifteen_minute_load": 7.45, "controller_cpu_system_time": 26060.0, "controller_cwd": "/home/jenkins/nstat/controllers/odl_beryllium_rc2_pb/distribution-karaf-0.4.0-Beryllium-RC2", "controller_java_xopts": ["-Xmx8G", "-Xms8G", "-XX:+UseG1GC", "-XX:MaxPermSize=8G"], "free_memory_bytes": 157365288, "controller_vm_size": 29637881856, "controller_cpu_shares": "75", "successful_bootup_time": 1578.3919248580933, "five_minute_load": 8.41, "global_sample_id": 4, "controller_statistics_period_ms": 5000, "controller_num_fds": 6585, "controller_node_ip": "192.168.100.1", "multinet_worker_topo_size": 300, "controller_cpu_user_time": 410794.0, "date": "Fri Mar  4 18:50:09 EET 2016", "max_discovered_switches": 4800, "one_minute_load": 9.68, "multinet_group_delay_ms": 5000, "multinet_size": 4800, "timestamp": 1457110209, "total_memory_bytes": 263927548, "bootup_time_secs": 1578.3919248580933, "controller_port": "6653"}, {"discovered_switches": 4800, "multinet_hosts_per_switch": 0, "multinet_group_size": 5, "discovered_switches_error_code": 0, "multinet_topology_type": "linear", "used_memory_bytes": 107454872, "controller_num_threads": 686, "multinet_workers": 16, "fifteen_minute_load": 14.77, "controller_cpu_system_time": 22797.0, "controller_cwd": "/home/jenkins/nstat/controllers/odl_beryllium_rc2_pb/distribution-karaf-0.4.0-Beryllium-RC2", "controller_java_xopts": ["-Xmx8G", "-Xms8G", "-XX:+UseG1GC", "-XX:MaxPermSize=8G"], "free_memory_bytes": 156472556, "controller_vm_size": 29691584512, "controller_cpu_shares": "75", "successful_bootup_time": 857.6255388259888, "five_minute_load": 20.64, "global_sample_id": 5, "controller_statistics_period_ms": 5000, "controller_num_fds": 6585, "controller_node_ip": "192.168.100.1", "multinet_worker_topo_size": 300, "controller_cpu_user_time": 371630.0, "date": "Fri Mar  4 19:08:35 EET 2016", "max_discovered_switches": 4800, "one_minute_load": 20.72, "multinet_group_delay_ms": 5000, "multinet_size": 4800, "timestamp": 1457111315, "total_memory_bytes": 263927548, "bootup_time_secs": 857.6255388259888, "controller_port": "6653"}, {"discovered_switches": 6400, "multinet_hosts_per_switch": 0, "multinet_group_size": 1, "discovered_switches_error_code": 0, "multinet_topology_type": "linear", "used_memory_bytes": 111019404, "controller_num_threads": 800, "multinet_workers": 16, "fifteen_minute_load": 19.82, "controller_cpu_system_time": 49091.0, "controller_cwd": "/home/jenkins/nstat/controllers/odl_beryllium_rc2_pb/distribution-karaf-0.4.0-Beryllium-RC2", "controller_java_xopts": ["-Xmx8G", "-Xms8G", "-XX:+UseG1GC", "-XX:MaxPermSize=8G"], "free_memory_bytes": 152906160, "controller_vm_size": 29809467392, "controller_cpu_shares": "75", "successful_bootup_time": 2348.419197320938, "five_minute_load": 26.45, "global_sample_id": 6, "controller_statistics_period_ms": 5000, "controller_num_fds": 8185, "controller_node_ip": "192.168.100.1", "multinet_worker_topo_size": 400, "controller_cpu_user_time": 834108.0, "date": "Fri Mar  4 19:52:03 EET 2016", "max_discovered_switches": 6400, "one_minute_load": 33.72, "multinet_group_delay_ms": 5000, "multinet_size": 6400, "timestamp": 1457113923, "total_memory_bytes": 263927548, "bootup_time_secs": 2348.419197320938, "controller_port": "6653"}, {"discovered_switches": 4814, "multinet_hosts_per_switch": 0, "multinet_group_size": 5, "discovered_switches_error_code": 201, "multinet_topology_type": "linear", "used_memory_bytes": 101444472, "controller_num_threads": -1, "multinet_workers": 16, "fifteen_minute_load": 16591.78, "controller_cpu_system_time": -1.0, "controller_cwd": "12653: No such process", "controller_java_xopts": [], "free_memory_bytes": 162483076, "controller_vm_size": -1024, "controller_cpu_shares": "75", "successful_bootup_time": -1, "five_minute_load": 27974.07, "global_sample_id": 7, "controller_statistics_period_ms": 5000, "controller_num_fds": -4, "controller_node_ip": "192.168.100.1", "multinet_worker_topo_size": 400, "controller_cpu_user_time": -1.0, "date": "Fri Mar  4 20:38:47 EET 2016", "max_discovered_switches": 6308, "one_minute_load": 27048.73, "multinet_group_delay_ms": 5000, "multinet_size": 6400, "timestamp": 1457116727, "total_memory_bytes": 263927548, "bootup_time_secs": 2413.123077392578, "controller_port": "6653"}, {"discovered_switches": 0, "multinet_hosts_per_switch": 0, "multinet_group_size": 1, "discovered_switches_error_code": 201, "multinet_topology_type": "linear", "used_memory_bytes": 99159704, "controller_num_threads": -1, "multinet_workers": 16, "fifteen_minute_load": 11448.76, "controller_cpu_system_time": -1.0, "controller_cwd": "5873: No such process", "controller_java_xopts": [], "free_memory_bytes": 164767112, "controller_vm_size": -1024, "controller_cpu_shares": "75", "successful_bootup_time": -1, "five_minute_load": 18711.95, "global_sample_id": 8, "controller_statistics_period_ms": 5000, "controller_num_fds": -4, "controller_node_ip": "192.168.100.1", "multinet_worker_topo_size": 500, "controller_cpu_user_time": -1.0, "date": "Fri Mar  4 21:31:00 EET 2016", "max_discovered_switches": 0, "one_minute_load": 8417.46, "multinet_group_delay_ms": 5000, "multinet_size": 8000, "timestamp": 1457119860, "total_memory_bytes": 263927548, "bootup_time_secs": 2668.6895015239716, "controller_port": "6653"}, {"discovered_switches": 7169, "multinet_hosts_per_switch": 0, "multinet_group_size": 5, "discovered_switches_error_code": 201, "multinet_topology_type": "linear", "used_memory_bytes": 101339044, "controller_num_threads": -1, "multinet_workers": 16, "fifteen_minute_load": 11923.26, "controller_cpu_system_time": -1.0, "controller_cwd": "44466: No such process", "controller_java_xopts": [], "free_memory_bytes": 162587708, "controller_vm_size": -1024, "controller_cpu_shares": "75", "successful_bootup_time": -1, "five_minute_load": 23049.79, "global_sample_id": 9, "controller_statistics_period_ms": 5000, "controller_num_fds": -4, "controller_node_ip": "192.168.100.1", "multinet_worker_topo_size": 500, "controller_cpu_user_time": -1.0, "date": "Fri Mar  4 22:15:11 EET 2016", "max_discovered_switches": 7390, "one_minute_load": 26830.75, "multinet_group_delay_ms": 5000, "multinet_size": 8000, "timestamp": 1457122511, "total_memory_bytes": 263927548, "bootup_time_secs": 2236.3880653381348, "controller_port": "6653"}, {"discovered_switches": 0, "multinet_hosts_per_switch": 0, "multinet_group_size": 1, "discovered_switches_error_code": 201, "multinet_topology_type": "linear", "used_memory_bytes": 104968192, "controller_num_threads": -1, "multinet_workers": 16, "fifteen_minute_load": 19202.84, "controller_cpu_system_time": -1.0, "controller_cwd": "44473: No such process", "controller_java_xopts": [], "free_memory_bytes": 158958452, "controller_vm_size": -1024, "controller_cpu_shares": "75", "successful_bootup_time": -1, "five_minute_load": 20244.91, "global_sample_id": 10, "controller_statistics_period_ms": 5000, "controller_num_fds": -4, "controller_node_ip": "192.168.100.1", "multinet_worker_topo_size": 600, "controller_cpu_user_time": -1.0, "date": "Fri Mar  4 23:19:49 EET 2016", "max_discovered_switches": 0, "one_minute_load": 3689.07, "multinet_group_delay_ms": 5000, "multinet_size": 9600, "timestamp": 1457126389, "total_memory_bytes": 263927548, "bootup_time_secs": 3341.093975543976, "controller_port": "6653"}, {"discovered_switches": 8141, "multinet_hosts_per_switch": 0, "multinet_group_size": 5, "discovered_switches_error_code": 201, "multinet_topology_type": "linear", "used_memory_bytes": 107555036, "controller_num_threads": -1, "multinet_workers": 16, "fifteen_minute_load": 14685.77, "controller_cpu_system_time": -1.0, "controller_cwd": "18175: No such process", "controller_java_xopts": [], "free_memory_bytes": 156370772, "controller_vm_size": -1024, "controller_cpu_shares": "75", "successful_bootup_time": -1, "five_minute_load": 26235.6, "global_sample_id": 11, "controller_statistics_period_ms": 5000, "controller_num_fds": -4, "controller_node_ip": "192.168.100.1", "multinet_worker_topo_size": 600, "controller_cpu_user_time": -1.0, "date": "Sat Mar  5 00:19:51 EET 2016", "max_discovered_switches": 8615, "one_minute_load": 27107.42, "multinet_group_delay_ms": 5000, "multinet_size": 9600, "timestamp": 1457129991, "total_memory_bytes": 263927548, "bootup_time_secs": 3155.9518184661865, "controller_port": "6653"}]